plotly01/__init__.py
plotly01/frontend/index.html
plotly01/frontend/main.js
plotly01/frontend/plotly-2.14.0.min.js
plotly01/frontend/streamlit-component-lib.js
plotly01-0.1.0.dist-info/LICENSE
plotly01-0.1.0.dist-info/METADATA
plotly01-0.1.0.dist-info/WHEEL
plotly01-0.1.0.dist-info/top_level.txt
plotly01-0.1.0.dist-info/RECORD
